if_else/__init__.py
if_else/mycode.py
if_else/run.py
add_two_num-0.0.1.dist-info/LICENSE
add_two_num-0.0.1.dist-info/METADATA
add_two_num-0.0.1.dist-info/WHEEL
add_two_num-0.0.1.dist-info/top_level.txt
add_two_num-0.0.1.dist-info/RECORD
